anospp_analysis/__init__.py
anospp_analysis/agg.py
anospp_analysis/iplot.py
anospp_analysis/nn.py
anospp_analysis/plasm.py
anospp_analysis/prep.py
anospp_analysis/qc.py
anospp_analysis/test_functions_vae.py
anospp_analysis/util.py
anospp_analysis/vae.py
anospp_analysis-0.4.0.dist-info/LICENSE
anospp_analysis-0.4.0.dist-info/METADATA
anospp_analysis-0.4.0.dist-info/WHEEL
anospp_analysis-0.4.0.dist-info/entry_points.txt
anospp_analysis-0.4.0.dist-info/RECORD
