Metadata-Version: 2.1
Name: anospp-analysis
Version: 0.4.0
Summary: ANOSPP data analysis
License: MIT
Author: Alex Makunin
Author-email: am60@sanger.ac.uk
Requires-Python: >=3.10,<3.11
Classifier: License :: OSI Approved :: MIT License
Classifier: Programming Language :: Python :: 3
Classifier: Programming Language :: Python :: 3.10
Requires-Dist: bokeh
Requires-Dist: cutadapt
Requires-Dist: keras (>=2.12,<3.0)
Requires-Dist: numpy
Requires-Dist: pandas
Requires-Dist: pyarrow
Requires-Dist: scipy
Requires-Dist: seaborn
Requires-Dist: tensorflow (>=2.12,<3.0)
